transpatter/__init__.py
transpatter/main.py
transpatter/prompts.py
transpatter-2025.12.21122704.dist-info/METADATA
transpatter-2025.12.21122704.dist-info/WHEEL
transpatter-2025.12.21122704.dist-info/top_level.txt
transpatter-2025.12.21122704.dist-info/RECORD
