Metadata-Version: 2.4
Name: transpatter
Version: 2025.12.21122704
Summary: A new package that leverages pattern matching with language models to generate structured summaries or insights from user-submitted texts about topics like train maps or other transportation issues. I
Author-email: transpatter <hi@eugene.plus>
License: MIT
Project-URL: Homepage, https://github.com/chigwell/transpatter
Requires-Python: >=3.9
Requires-Dist: langchain-llm7>=0.0.0
Requires-Dist: llmatch-messages>=0.0.0
Requires-Dist: langchain-core>=0.3.0
